webrute/__init__.py
webrute/_attributes.py
webrute/_connector.py
webrute/_functions.py
webrute/_highlevel.py
webrute/_runner.py
webrute/_util.py
webrute/exceptions.py
webrute-0.2.1.dist-info/LICENSE
webrute-0.2.1.dist-info/METADATA
webrute-0.2.1.dist-info/WHEEL
webrute-0.2.1.dist-info/top_level.txt
webrute-0.2.1.dist-info/RECORD
