Metadata-Version: 2.1
Name: webrute
Version: 0.2.1
Summary: Python bruteforce library for http requests
Home-page: https://github.com/sekgobela-kevin/webrute
Author: Sekgobela Kevin
Author-email: kevinnoko23@gmail.com
Project-URL: Bug Tracker, https://github.com/sekgobela-kevin/webrute/issues
Keywords: login,website,html-form,secutity,hacking,bruteforce
Classifier: Intended Audience :: Developers
Classifier: Development Status :: 2 - Pre-Alpha
Classifier: License :: OSI Approved :: GNU General Public License v3 (GPLv3)
Classifier: Programming Language :: Python
Classifier: Programming Language :: Python :: 3
Classifier: Topic :: Security
Classifier: Topic :: Software Development
Classifier: Topic :: Software Development :: Libraries
Classifier: Topic :: Software Development :: Libraries :: Python Modules
Requires-Python: >=3.6
License-File: LICENSE
Requires-Dist: broote (<0.7.0,>=0.6.0)
Requires-Dist: httpx
